[
  {
    "idx": 1,
    "name": "seedb-003|CF电信优选",
    "http_code": "204",
    "check_s": "1.736579",
    "speed_s": "6.006243",
    "speed_bps": 51786.0
  },
  {
    "idx": 2,
    "name": "seede-021|CF电信优选",
    "http_code": "204",
    "check_s": "1.984684",
    "speed_s": "5.326493",
    "speed_bps": 196860.0
  },
  {
    "idx": 3,
    "name": "edge4-016|CF电信优选",
    "http_code": "000",
    "check_s": "4.006491",
    "speed_s": "",
    "speed_bps": 0.0
  },
  {
    "idx": 4,
    "name": "seede-015|CF电信优选",
    "http_code": "204",
    "check_s": "2.380249",
    "speed_s": "5.212406",
    "speed_bps": 201169.0
  },
  {
    "idx": 5,
    "name": "seedf-010|CF电信优选",
    "http_code": "000",
    "check_s": "4.002656",
    "speed_s": "",
    "speed_bps": 0.0
  },
  {
    "idx": 6,
    "name": "seedd-012|CF电信优选",
    "http_code": "204",
    "check_s": "3.139761",
    "speed_s": "5.793324",
    "speed_bps": 180997.0
  },
  {
    "idx": 7,
    "name": "seeda-017|CF电信优选",
    "http_code": "204",
    "check_s": "2.822605",
    "speed_s": "5.097377",
    "speed_bps": 205708.0
  },
  {
    "idx": 8,
    "name": "seede-017|CF电信优选",
    "http_code": "204",
    "check_s": "3.513009",
    "speed_s": "6.005610",
    "speed_bps": 166372.0
  },
  {
    "idx": 9,
    "name": "seedd-013|CF电信优选",
    "http_code": "204",
    "check_s": "2.120189",
    "speed_s": "5.115857",
    "speed_bps": 204965.0
  },
  {
    "idx": 10,
    "name": "seedb-029|CF电信优选",
    "http_code": "204",
    "check_s": "3.400691",
    "speed_s": "5.573042",
    "speed_bps": 188151.0
  },
  {
    "idx": 11,
    "name": "seede-013|CF电信优选",
    "http_code": "204",
    "check_s": "1.743560",
    "speed_s": "5.613297",
    "speed_bps": 186802.0
  },
  {
    "idx": 12,
    "name": "reedge-006|CF电信优选",
    "http_code": "204",
    "check_s": "1.152194",
    "speed_s": "4.478154",
    "speed_bps": 234153.0
  },
  {
    "idx": 13,
    "name": "seedb-009|CF电信优选",
    "http_code": "204",
    "check_s": "1.465576",
    "speed_s": "6.002642",
    "speed_bps": 76382.0
  },
  {
    "idx": 14,
    "name": "edge4-022|CF电信优选",
    "http_code": "204",
    "check_s": "1.269926",
    "speed_s": "6.003711",
    "speed_bps": 76369.0
  },
  {
    "idx": 15,
    "name": "seedf-005|CF电信优选",
    "http_code": "204",
    "check_s": "1.170160",
    "speed_s": "6.004040",
    "speed_bps": 13602.0
  },
  {
    "idx": 16,
    "name": "seedf-014|CF电信优选",
    "http_code": "000",
    "check_s": "4.011278",
    "speed_s": "",
    "speed_bps": 0.0
  },
  {
    "idx": 17,
    "name": "seeda-002|CF电信优选",
    "http_code": "204",
    "check_s": "2.657106",
    "speed_s": "4.641904",
    "speed_bps": 225893.0
  },
  {
    "idx": 18,
    "name": "seedf-023|CF电信优选",
    "http_code": "204",
    "check_s": "1.697851",
    "speed_s": "6.002727",
    "speed_bps": 98217.0
  },
  {
    "idx": 19,
    "name": "seedd-002|CF电信优选",
    "http_code": "204",
    "check_s": "1.511300",
    "speed_s": "6.001504",
    "speed_bps": 40907.0
  },
  {
    "idx": 20,
    "name": "edge1-015|CF电信优选",
    "http_code": "204",
    "check_s": "3.982858",
    "speed_s": "6.001817",
    "speed_bps": 19066.0
  },
  {
    "idx": 21,
    "name": "seede-008|CF电信优选",
    "http_code": "204",
    "check_s": "1.434450",
    "speed_s": "6.000866",
    "speed_bps": 111899.0
  },
  {
    "idx": 22,
    "name": "seedb-016|CF电信优选",
    "http_code": "204",
    "check_s": "2.673452",
    "speed_s": "6.003110",
    "speed_bps": 54542.0
  },
  {
    "idx": 23,
    "name": "reedge-025|CF电信优选",
    "http_code": "000",
    "check_s": "4.002960",
    "speed_s": "",
    "speed_bps": 0.0
  },
  {
    "idx": 24,
    "name": "seeda-018|CF电信优选",
    "http_code": "204",
    "check_s": "3.664582",
    "speed_s": "6.004497",
    "speed_bps": 120017.0
  },
  {
    "idx": 25,
    "name": "seedb-021|CF电信优选",
    "http_code": "000",
    "check_s": "4.002385",
    "speed_s": "",
    "speed_bps": 0.0
  },
  {
    "idx": 26,
    "name": "seede-026|CF电信优选",
    "http_code": "204",
    "check_s": "2.529801",
    "speed_s": "6.005875",
    "speed_bps": 98165.0
  },
  {
    "idx": 27,
    "name": "seedb-013|CF电信优选",
    "http_code": "204",
    "check_s": "1.425668",
    "speed_s": "6.001301",
    "speed_bps": 19068.0
  },
  {
    "idx": 28,
    "name": "seedf-007|CF电信优选",
    "http_code": "204",
    "check_s": "3.623183",
    "speed_s": "6.002936",
    "speed_bps": 19063.0
  },
  {
    "idx": 29,
    "name": "seeda-024|CF电信优选",
    "http_code": "204",
    "check_s": "1.136890",
    "speed_s": "6.001262",
    "speed_bps": 169223.0
  },
  {
    "idx": 30,
    "name": "seedb-030|CF电信优选",
    "http_code": "204",
    "check_s": "1.422818",
    "speed_s": "6.005877",
    "speed_bps": 32693.0
  },
  {
    "idx": 31,
    "name": "seede-001|CF电信优选",
    "http_code": "204",
    "check_s": "2.182376",
    "speed_s": "5.831733",
    "speed_bps": 179805.0
  },
  {
    "idx": 32,
    "name": "reedge-005|CF电信优选",
    "http_code": "204",
    "check_s": "1.221911",
    "speed_s": "6.000448",
    "speed_bps": 117367.0
  },
  {
    "idx": 33,
    "name": "seedb-019|CF电信优选",
    "http_code": "000",
    "check_s": "4.004279",
    "speed_s": "",
    "speed_bps": 0.0
  },
  {
    "idx": 34,
    "name": "edge1-028|CF电信优选",
    "http_code": "204",
    "check_s": "1.717213",
    "speed_s": "6.002481",
    "speed_bps": 73655.0
  },
  {
    "idx": 35,
    "name": "seedf-019|CF电信优选",
    "http_code": "204",
    "check_s": "2.894909",
    "speed_s": "6.003945",
    "speed_bps": 100926.0
  },
  {
    "idx": 36,
    "name": "edge4-027|CF电信优选",
    "http_code": "204",
    "check_s": "2.689700",
    "speed_s": "4.912887",
    "speed_bps": 213433.0
  },
  {
    "idx": 37,
    "name": "seeda-009|CF电信优选",
    "http_code": "204",
    "check_s": "2.861542",
    "speed_s": "5.722916",
    "speed_bps": 183224.0
  },
  {
    "idx": 38,
    "name": "edge1-009|CF电信优选",
    "http_code": "204",
    "check_s": "1.438702",
    "speed_s": "4.496166",
    "speed_bps": 233215.0
  },
  {
    "idx": 39,
    "name": "seedd-017|CF电信优选",
    "http_code": "204",
    "check_s": "3.539172",
    "speed_s": "6.006623",
    "speed_bps": 109064.0
  },
  {
    "idx": 40,
    "name": "seedf-015|CF电信优选",
    "http_code": "204",
    "check_s": "2.845217",
    "speed_s": "",
    "speed_bps": 0.0
  },
  {
    "idx": 41,
    "name": "reedge-019|CF电信优选",
    "http_code": "204",
    "check_s": "1.166012",
    "speed_s": "6.005266",
    "speed_bps": 81806.0
  },
  {
    "idx": 42,
    "name": "seedb-018|CF电信优选",
    "http_code": "204",
    "check_s": "3.485894",
    "speed_s": "6.004771",
    "speed_bps": 150025.0
  },
  {
    "idx": 43,
    "name": "seedd-019|CF电信优选",
    "http_code": "204",
    "check_s": "1.119383",
    "speed_s": "6.003636",
    "speed_bps": 117305.0
  },
  {
    "idx": 44,
    "name": "edge4-005|CF电信优选",
    "http_code": "204",
    "check_s": "1.477305",
    "speed_s": "6.002459",
    "speed_bps": 2687.0
  },
  {
    "idx": 45,
    "name": "edge4-021|CF电信优选",
    "http_code": "000",
    "check_s": "4.002437",
    "speed_s": "",
    "speed_bps": 0.0
  },
  {
    "idx": 46,
    "name": "seede-006|CF电信优选",
    "http_code": "204",
    "check_s": "2.464002",
    "speed_s": "",
    "speed_bps": 0.0
  },
  {
    "idx": 47,
    "name": "seedd-020|CF电信优选",
    "http_code": "204",
    "check_s": "2.765647",
    "speed_s": "6.000582",
    "speed_bps": 90061.0
  },
  {
    "idx": 48,
    "name": "seede-014|CF电信优选",
    "http_code": "204",
    "check_s": "1.179183",
    "speed_s": "6.000150",
    "speed_bps": 103720.0
  },
  {
    "idx": 49,
    "name": "seede-025|CF电信优选",
    "http_code": "204",
    "check_s": "1.895330",
    "speed_s": "4.376733",
    "speed_bps": 239579.0
  },
  {
    "idx": 50,
    "name": "seedd-011|CF电信优选",
    "http_code": "000",
    "check_s": "4.002568",
    "speed_s": "",
    "speed_bps": 0.0
  },
  {
    "idx": 51,
    "name": "edge4-017|CF电信优选",
    "http_code": "204",
    "check_s": "1.137251",
    "speed_s": "6.001589",
    "speed_bps": 117345.0
  },
  {
    "idx": 52,
    "name": "edge4-003|CF电信优选",
    "http_code": "204",
    "check_s": "2.996152",
    "speed_s": "5.699799",
    "speed_bps": 183967.0
  },
  {
    "idx": 53,
    "name": "seedf-008|CF电信优选",
    "http_code": "000",
    "check_s": "4.006823",
    "speed_s": "",
    "speed_bps": 0.0
  },
  {
    "idx": 54,
    "name": "seede-019|CF电信优选",
    "http_code": "204",
    "check_s": "2.111410",
    "speed_s": "6.000663",
    "speed_bps": 43643.0
  },
  {
    "idx": 55,
    "name": "reedge-030|CF电信优选",
    "http_code": "204",
    "check_s": "1.457520",
    "speed_s": "5.893891",
    "speed_bps": 177908.0
  },
  {
    "idx": 56,
    "name": "seeda-005|CF电信优选",
    "http_code": "204",
    "check_s": "1.418340",
    "speed_s": "5.955915",
    "speed_bps": 176056.0
  },
  {
    "idx": 57,
    "name": "reedge-031|CF电信优选",
    "http_code": "000",
    "check_s": "4.006515",
    "speed_s": "",
    "speed_bps": 0.0
  },
  {
    "idx": 58,
    "name": "edge4-008|CF电信优选",
    "http_code": "204",
    "check_s": "1.131507",
    "speed_s": "",
    "speed_bps": 0.0
  },
  {
    "idx": 59,
    "name": "seeda-008|CF电信优选",
    "http_code": "204",
    "check_s": "1.901038",
    "speed_s": "6.000401",
    "speed_bps": 155595.0
  },
  {
    "idx": 60,
    "name": "reedge-008|CF电信优选",
    "http_code": "204",
    "check_s": "2.345377",
    "speed_s": "6.001221",
    "speed_bps": 120082.0
  },
  {
    "idx": 61,
    "name": "seedd-001|CF电信优选",
    "http_code": "204",
    "check_s": "1.117691",
    "speed_s": "6.003094",
    "speed_bps": 5416.0
  },
  {
    "idx": 62,
    "name": "seede-011|CF电信优选",
    "http_code": "000",
    "check_s": "4.003051",
    "speed_s": "",
    "speed_bps": 0.0
  },
  {
    "idx": 63,
    "name": "seeda-004|CF电信优选",
    "http_code": "204",
    "check_s": "2.558754",
    "speed_s": "6.003723",
    "speed_bps": 32705.0
  },
  {
    "idx": 64,
    "name": "edge1-008|CF电信优选",
    "http_code": "000",
    "check_s": "4.001778",
    "speed_s": "",
    "speed_bps": 0.0
  },
  {
    "idx": 65,
    "name": "seedb-010|CF电信优选",
    "http_code": "204",
    "check_s": "1.170096",
    "speed_s": "",
    "speed_bps": 0.0
  },
  {
    "idx": 66,
    "name": "edge1-001|CF电信优选",
    "http_code": "204",
    "check_s": "1.122070",
    "speed_s": "4.946883",
    "speed_bps": 211967.0
  },
  {
    "idx": 67,
    "name": "edge1-007|CF电信优选",
    "http_code": "204",
    "check_s": "1.164978",
    "speed_s": "5.649629",
    "speed_bps": 185600.0
  },
  {
    "idx": 68,
    "name": "seede-028|CF电信优选",
    "http_code": "204",
    "check_s": "1.980369",
    "speed_s": "",
    "speed_bps": 0.0
  },
  {
    "idx": 69,
    "name": "seedf-004|CF电信优选",
    "http_code": "204",
    "check_s": "1.569367",
    "speed_s": "6.011962",
    "speed_bps": 119868.0
  },
  {
    "idx": 70,
    "name": "seede-030|CF电信优选",
    "http_code": "204",
    "check_s": "2.188506",
    "speed_s": "5.175089",
    "speed_bps": 202619.0
  },
  {
    "idx": 71,
    "name": "edge1-032|CF电信优选",
    "http_code": "204",
    "check_s": "2.206360",
    "speed_s": "6.011320",
    "speed_bps": 114429.0
  },
  {
    "idx": 72,
    "name": "edge4-026|CF电信优选",
    "http_code": "204",
    "check_s": "1.127973",
    "speed_s": "",
    "speed_bps": 0.0
  },
  {
    "idx": 73,
    "name": "seede-031|CF电信优选",
    "http_code": "204",
    "check_s": "3.101110",
    "speed_s": "6.007133",
    "speed_bps": 19049.0
  },
  {
    "idx": 74,
    "name": "reedge-017|CF电信优选",
    "http_code": "204",
    "check_s": "2.798243",
    "speed_s": "5.963564",
    "speed_bps": 175830.0
  },
  {
    "idx": 75,
    "name": "reedge-010|CF电信优选",
    "http_code": "204",
    "check_s": "1.481200",
    "speed_s": "6.004597",
    "speed_bps": 90000.0
  },
  {
    "idx": 76,
    "name": "seede-016|CF电信优选",
    "http_code": "204",
    "check_s": "1.115171",
    "speed_s": "5.649928",
    "speed_bps": 185591.0
  },
  {
    "idx": 77,
    "name": "reedge-013|CF电信优选",
    "http_code": "204",
    "check_s": "2.093370",
    "speed_s": "5.441941",
    "speed_bps": 192684.0
  },
  {
    "idx": 78,
    "name": "seedd-031|CF电信优选",
    "http_code": "204",
    "check_s": "2.464062",
    "speed_s": "5.220452",
    "speed_bps": 200859.0
  },
  {
    "idx": 79,
    "name": "seedd-014|CF电信优选",
    "http_code": "204",
    "check_s": "3.425512",
    "speed_s": "6.002057",
    "speed_bps": 163741.0
  },
  {
    "idx": 80,
    "name": "edge4-001|CF电信优选",
    "http_code": "204",
    "check_s": "1.985263",
    "speed_s": "5.742222",
    "speed_bps": 182608.0
  },
  {
    "idx": 81,
    "name": "seedf-009|CF电信优选",
    "http_code": "204",
    "check_s": "2.229854",
    "speed_s": "6.001483",
    "speed_bps": 103697.0
  },
  {
    "idx": 82,
    "name": "seedb-001|CF电信优选",
    "http_code": "204",
    "check_s": "1.461840",
    "speed_s": "6.002727",
    "speed_bps": 95487.0
  },
  {
    "idx": 83,
    "name": "seedd-006|CF电信优选",
    "http_code": "204",
    "check_s": "2.998475",
    "speed_s": "6.005344",
    "speed_bps": 160923.0
  },
  {
    "idx": 84,
    "name": "seeda-014|CF电信优选",
    "http_code": "204",
    "check_s": "1.434619",
    "speed_s": "",
    "speed_bps": 0.0
  },
  {
    "idx": 85,
    "name": "edge1-014|CF电信优选",
    "http_code": "204",
    "check_s": "3.651106",
    "speed_s": "6.005081",
    "speed_bps": 130918.0
  },
  {
    "idx": 86,
    "name": "edge4-032|CF电信优选",
    "http_code": "204",
    "check_s": "1.871583",
    "speed_s": "6.003096",
    "speed_bps": 81835.0
  },
  {
    "idx": 87,
    "name": "edge4-029|CF电信优选",
    "http_code": "204",
    "check_s": "1.133234",
    "speed_s": "",
    "speed_bps": 0.0
  },
  {
    "idx": 88,
    "name": "seede-027|CF电信优选",
    "http_code": "204",
    "check_s": "2.098737",
    "speed_s": "5.321785",
    "speed_bps": 197034.0
  },
  {
    "idx": 89,
    "name": "edge1-031|CF电信优选",
    "http_code": "204",
    "check_s": "1.867940",
    "speed_s": "5.488213",
    "speed_bps": 191059.0
  },
  {
    "idx": 90,
    "name": "reedge-007|CF电信优选",
    "http_code": "204",
    "check_s": "2.243373",
    "speed_s": "5.993803",
    "speed_bps": 174943.0
  },
  {
    "idx": 91,
    "name": "seede-010|CF电信优选",
    "http_code": "204",
    "check_s": "1.114382",
    "speed_s": "6.001548",
    "speed_bps": 128266.0
  },
  {
    "idx": 92,
    "name": "seedb-024|CF电信优选",
    "http_code": "204",
    "check_s": "1.145082",
    "speed_s": "6.004328",
    "speed_bps": 84547.0
  },
  {
    "idx": 93,
    "name": "seede-029|CF电信优选",
    "http_code": "204",
    "check_s": "1.414204",
    "speed_s": "4.905089",
    "speed_bps": 213773.0
  },
  {
    "idx": 94,
    "name": "seedf-028|CF电信优选",
    "http_code": "204",
    "check_s": "2.701775",
    "speed_s": "4.252205",
    "speed_bps": 246595.0
  },
  {
    "idx": 95,
    "name": "seedd-021|CF电信优选",
    "http_code": "204",
    "check_s": "2.443705",
    "speed_s": "6.001261",
    "speed_bps": 68210.0
  },
  {
    "idx": 96,
    "name": "seedf-018|CF电信优选",
    "http_code": "204",
    "check_s": "1.418439",
    "speed_s": "6.004858",
    "speed_bps": 160936.0
  }
]