{
  "probe_count": 3,
  "configured_priority_probe": "winbox",
  "alive_fast_by_probe": {
    "winbox": 31,
    "zhongb-tail": 48,
    "local": 48
  },
  "mainland_probes": [
    "winbox",
    "zhongb-tail"
  ],
  "excluded_zero_yield_probes": [],
  "effective_probe_count": 3,
  "priority_probe": "winbox",
  "mainland_confirmed": true,
  "mainland_confirming_probes": [
    "winbox",
    "zhongb-tail"
  ],
  "gate": "ok",
  "shared_candidates": 48,
  "selected": 48,
  "priority_top_speed_bps": 502953.0,
  "top_min_speed_bps": 293457.0,
  "top_avg_speed_bps": 469755.0,
  "median_min_speed_bps": 333103.0,
  "min_of_selected_bps": 79011.0
}