{
  "probe_count": 3,
  "configured_priority_probe": "winbox",
  "alive_fast_by_probe": {
    "winbox": 87,
    "zhongb-tail": 48,
    "local": 105
  },
  "mainland_probes": [
    "winbox",
    "zhongb-tail"
  ],
  "excluded_zero_yield_probes": [],
  "effective_probe_count": 3,
  "priority_probe": "winbox",
  "mainland_confirmed": true,
  "mainland_confirming_probes": [
    "winbox",
    "zhongb-tail"
  ],
  "gate": "ok",
  "shared_candidates": 94,
  "selected": 40,
  "selected_by_country": {
    "SG": 10,
    "JP": 10,
    "<none>": 8,
    "US": 8,
    "HK": 4
  },
  "country_min_per_group": 4,
  "priority_top_speed_bps": 379877.0,
  "top_min_speed_bps": 69912.0,
  "top_avg_speed_bps": 299727.3333333333,
  "median_min_speed_bps": 117203.0,
  "min_of_selected_bps": 51774.0
}