{
  "probe_count": 3,
  "configured_priority_probe": "winbox",
  "alive_fast_by_probe": {
    "winbox": 107,
    "zhongb-tail": 48,
    "local": 107
  },
  "mainland_probes": [
    "winbox",
    "zhongb-tail"
  ],
  "excluded_zero_yield_probes": [],
  "effective_probe_count": 3,
  "priority_probe": "winbox",
  "mainland_confirmed": true,
  "mainland_confirming_probes": [
    "winbox",
    "zhongb-tail"
  ],
  "gate": "ok",
  "shared_candidates": 104,
  "selected": 40,
  "selected_by_country": {
    "US": 19,
    "JP": 5,
    "GB": 5,
    "SG": 3,
    "HK": 5,
    "DE": 3
  },
  "country_min_per_group": 4,
  "priority_top_speed_bps": 509705.0,
  "top_min_speed_bps": 404302.0,
  "top_avg_speed_bps": 457003.5,
  "median_min_speed_bps": 368612.0,
  "min_of_selected_bps": 281488.0
}